Metadata-Version: 1.1
Name: Flask-Pika-NG
Version: 0.3.3
Summary: Pika amqp flask extension
Home-page: https://github.com/experimentaltelephony/flask-pika
Author: Charlie Wolf
Author-email: charlie@flow180.com
License: BSD
Platform: any
Classifier: Environment :: Web Environment
Classifier: Intended Audience :: Developers
Classifier: Operating System :: OS Independent
Classifier: Programming Language :: Python
Classifier: Topic :: Internet :: WWW/HTTP :: Dynamic Content
Classifier: Topic :: Software Development :: Libraries :: Python Modules
